gameinventory/Inventory.py
gameinventory/Item.py
gameinventory/__init__.py
gameinventory-0.1.1.dist-info/METADATA
gameinventory-0.1.1.dist-info/WHEEL
gameinventory-0.1.1.dist-info/licenses/LICENSE
gameinventory-0.1.1.dist-info/RECORD
