Metadata-Version: 2.4
Name: gameinventory
Version: 0.1.1
Summary: A simple game inventory manager
Project-URL: Homepage, https://github.com/dhogenson/gameinventory
Project-URL: Issues, https://github.com/dhogenson/gameinventory/issues
Author-email: Dallin Hogenson <dallin.hogenson@icloud.com>
License-Expression: MIT
License-File: LICENSE
Classifier: Operating System :: OS Independent
Classifier: Programming Language :: Python :: 3
Requires-Python: >=3.9
